ratesb_web/__init__.py
ratesb_web/common/__init__.py
ratesb_web/common/analyzer.py
ratesb_web/common/custom_classifier.py
ratesb_web/common/default_classifier.json
ratesb_web/common/messages.json
ratesb_web/common/reaction_data.py
ratesb_web/common/results.py
ratesb_web/common/util.py
tests/__init__.py
tests/test_analyzer.py
tests/test_classifier.py
tests/test_results.py
tests/test_util.py
ratesb_web-0.1.1.dist-info/LICENSE
ratesb_web-0.1.1.dist-info/METADATA
ratesb_web-0.1.1.dist-info/WHEEL
ratesb_web-0.1.1.dist-info/top_level.txt
ratesb_web-0.1.1.dist-info/RECORD
