Metadata-Version: 2.1
Name: ratesb_web
Version: 0.1.1
Summary: backend support for ratesb
Home-page: https://github.com/sys-bio/ratesb_web
Author: Longxuan Fan
Author-email: Longxuan Fan <longxuan@usc.edu>
License: MIT License
Classifier: Programming Language :: Python :: 3
Classifier: Operating System :: OS Independent
Requires-Python: >=3.8
License-File: LICENSE
Requires-Dist: sympy
